MANIFEST.in
setup.py
pynode/__init__.py
pynode/exceptions.py
pynode/content/node/entrypoint-http.js
pynode/content/node/entrypoint-stream.js
pynode/hosting_models/__init__.py
pynode/hosting_models/http_node_instance.py
pynode/hosting_models/io_node_instance.py
pynode/hosting_models/out_of_process_node_instance.py
pynode/runners/BabelRunner.py
pynode/runners/NodeRunner.py
pynode/runners/Runner.py
pynode/runners/__init__.py
python_node.egg-info/PKG-INFO
python_node.egg-info/SOURCES.txt
python_node.egg-info/dependency_links.txt
python_node.egg-info/requires.txt
python_node.egg-info/top_level.txt