Metadata-Version: 1.0
Name: python-node
Version: 0.0.3
Summary: A node.js script runner for python
Home-page: https://github.com/ptMuta/python-node
Author: Joona Romppanen
Author-email: joona.romppanen@gmail.com
License: UNKNOWN
Platform: UNKNOWN
